aim/VERSION
aim/__about__.py
aim/__init__.py
aim/__version__.py
aim/acme.py
aim/catboost.py
aim/distributed_hugging_face.py
aim/fastai.py
aim/hf_dataset.py
aim/hugging_face.py
aim/keras.py
aim/keras_tuner.py
aim/lightgbm.py
aim/mxnet.py
aim/optuna.py
aim/paddle.py
aim/prophet.py
aim/py.typed
aim/pytorch.py
aim/pytorch_ignite.py
aim/pytorch_lightning.py
aim/sb3.py
aim/tensorflow.py
aim/xgboost.py
aim/cli/__init__.py
aim/cli/cli.py
aim/cli/configs.py
aim/cli/utils.py
aim/cli/watcher_cli.py
aim/cli/convert/__init__.py
aim/cli/convert/commands.py
aim/cli/convert/processors/__init__.py
aim/cli/convert/processors/mlflow.py
aim/cli/convert/processors/tensorboard.py
aim/cli/convert/processors/wandb.py
aim/cli/init/__init__.py
aim/cli/init/commands.py
aim/cli/manager/__init__.py
aim/cli/manager/manager.py
aim/cli/runs/__init__.py
aim/cli/runs/commands.py
aim/cli/runs/utils.py
aim/cli/server/__init__.py
aim/cli/server/commands.py
aim/cli/storage/__init__.py
aim/cli/storage/commands.py
aim/cli/up/__init__.py
aim/cli/up/commands.py
aim/cli/version/__init__.py
aim/cli/version/commands.py
aim/ext/__init__.py
aim/ext/exception_resistant.py
aim/ext/pynvml.py
aim/ext/utils.py
aim/ext/cleanup/__init__.py
aim/ext/notebook/__init__.py
aim/ext/notebook/notebook.py
aim/ext/notifier/__init__.py
aim/ext/notifier/base_notifier.py
aim/ext/notifier/config.py
aim/ext/notifier/config_default.json
aim/ext/notifier/config_empty.json
aim/ext/notifier/logging_notifier.py
aim/ext/notifier/notifier.py
aim/ext/notifier/notifier_builder.py
aim/ext/notifier/slack_notifier.py
aim/ext/notifier/utils.py
aim/ext/notifier/workplace_notifier.py
aim/ext/resource/__init__.py
aim/ext/resource/configs.py
aim/ext/resource/log.py
aim/ext/resource/stat.py
aim/ext/resource/tracker.py
aim/ext/resource/utils.py
aim/ext/sshfs/__init__.py
aim/ext/sshfs/utils.py
aim/ext/task_queue/__init__.py
aim/ext/task_queue/queue.py
aim/ext/tensorboard_tracker/__init__.py
aim/ext/tensorboard_tracker/run.py
aim-3.29.1.dist-info/licenses/LICENSE
aim-3.29.1.dist-info/METADATA
aim-3.29.1.dist-info/WHEEL
aim-3.29.1.dist-info/entry_points.txt
aim-3.29.1.dist-info/top_level.txt
aim-3.29.1.dist-info/RECORD
