Metadata-Version: 2.4
Name: aim
Version: 3.29.1
Summary: A super-easy way to record, search and compare AI experiments.
Classifier: License :: OSI Approved :: Apache Software License
Classifier: Programming Language :: Python
Classifier: Programming Language :: Python :: 3
Classifier: Programming Language :: Python :: 3.7
Classifier: Programming Language :: Python :: 3.8
Classifier: Programming Language :: Python :: 3.9
Classifier: Programming Language :: Python :: 3.10
Classifier: Programming Language :: Python :: 3.11
Classifier: Programming Language :: Python :: 3.12
Classifier: Programming Language :: Python :: Implementation :: PyPy
Requires-Python: >=3.7.0
License-File: LICENSE
Requires-Dist: aim-ui==3.29.1
Requires-Dist: aimrecords==0.0.7
Requires-Dist: aimrocks==0.5.*
Requires-Dist: cachetools>=4.0.0
Requires-Dist: click>=7.0
Requires-Dist: cryptography>=3.0
Requires-Dist: filelock<4,>=3.3.0
Requires-Dist: numpy<3,>=1.12.0
Requires-Dist: psutil>=5.6.7
Requires-Dist: RestrictedPython>=5.1
Requires-Dist: tqdm>=4.20.0
Requires-Dist: aiofiles>=0.5.0
Requires-Dist: alembic<2,>=1.5.0
Requires-Dist: fastapi<1,>=0.69.0
Requires-Dist: jinja2<4,>=2.10.0
Requires-Dist: pytz>=2019.1
Requires-Dist: SQLAlchemy>=1.4.1
Requires-Dist: uvicorn<1,>=0.12.0
Requires-Dist: Pillow>=8.0.0
Requires-Dist: packaging>=15.0
Requires-Dist: python-dateutil
Requires-Dist: requests
Requires-Dist: watchdog
Requires-Dist: websockets
Requires-Dist: boto3
Dynamic: classifier
Dynamic: description
Dynamic: description-content-type
Dynamic: license-file
Dynamic: requires-dist
Dynamic: requires-python
Dynamic: summary
